yflive/__init__.py
yflive/_logger.py
yflive/_reader.py
yflive/quote.py
yflive/streamer.py
yflive/yfquote_pb2.py
yflive/enums/__init__.py
yflive/enums/market_state.py
yflive/enums/option_type.py
yflive/enums/quote_type.py
yflive-1.0.0.dist-info/LICENSE.txt
yflive-1.0.0.dist-info/METADATA
yflive-1.0.0.dist-info/WHEEL
yflive-1.0.0.dist-info/top_level.txt
yflive-1.0.0.dist-info/RECORD
