Metadata-Version: 2.1
Name: yflive
Version: 1.0.0
Summary: live Yahoo! Finance data streamer
Home-page: https://github.com/mbnlc/yflive.git
Author: Max Beinlich
Author-email: maxbeinlich@gmail.com
License: Apache
Download-URL: https://github.com/mbnlc/yflive/releases
Project-URL: Source, https://github.com/mbnlc/yflive
Project-URL: Bug Tracker, https://github.com/mbnlc/yflive/issues
Platform: UNKNOWN
Classifier: Development Status :: 5 - Production/Stable
Classifier: Programming Language :: Python
Classifier: Programming Language :: Python :: 3
Classifier: Programming Language :: Python :: 3.6
Classifier: Programming Language :: Python :: 3.7
Classifier: Programming Language :: Python :: 3.8
Classifier: Programming Language :: Python :: 3.9
Classifier: Operating System :: OS Independent
Classifier: License :: OSI Approved :: Apache Software License
Classifier: Intended Audience :: Developers
Classifier: Topic :: Office/Business :: Financial
Classifier: Topic :: Office/Business :: Financial :: Investment
Classifier: Topic :: Software Development :: Libraries
Classifier: Topic :: Software Development :: Libraries :: Python Modules
Requires-Python: >=3.6
Requires-Dist: websocket-client
Requires-Dist: protobuf
